shadowCut/CustomModel.py
shadowCut/PreTrainedModel.py
shadowCut/ResizeImage.py
shadowCut/__init__.py
shadowCut/constants.py
shadowCut-1.0.6.dist-info/LICENSE
shadowCut-1.0.6.dist-info/METADATA
shadowCut-1.0.6.dist-info/WHEEL
shadowCut-1.0.6.dist-info/top_level.txt
shadowCut-1.0.6.dist-info/RECORD
