Metadata-Version: 2.1
Name: shadowCut
Version: 1.0.6
Summary: Deep Learning Library to speed up the coding process
Home-page: UNKNOWN
Author: Aayush Jain
Author-email: jainaayush99.aj@gmail.com
License: MIT
Platform: UNKNOWN
Classifier: Development Status :: 5 - Production/Stable
Classifier: Intended Audience :: Education
Classifier: Operating System :: Microsoft :: Windows :: Windows 10
Classifier: License :: OSI Approved :: MIT License
Classifier: Programming Language :: Python :: 3
Requires-Dist: Pillow
Requires-Dist: tensorflow
Requires-Dist: glob2
